ubiquitysoftware/VERSION
ubiquitysoftware/__init__.py
ubiquitysoftware/argument_parser.py
ubiquitysoftware/model.py
ubiquitysoftware/ubiquity_student.py
ubiquitysoftware/version.py
ubiquitysoftware/controllers/__init__.py
ubiquitysoftware/controllers/config_file.py
ubiquitysoftware/controllers/main_controller.py
ubiquitysoftware/controllers/worker.py
ubiquitysoftware/images/add_folder_icn.png
ubiquitysoftware/images/icon.icns
ubiquitysoftware/images/icon.ico
ubiquitysoftware/images/search_icn.png
ubiquitysoftware/images/ubiquity_icon.png
ubiquitysoftware/locale/fr/LC_MESSAGES/ubiquity-student.mo
ubiquitysoftware/tktooltip/__init__.py
ubiquitysoftware/tktooltip/tooltip.py
ubiquitysoftware/tktooltip/version.py
ubiquitysoftware/views/__init__.py
ubiquitysoftware/views/utils.py
ubiquitysoftware/views/cui/__init__.py
ubiquitysoftware/views/cui/main_view.py
ubiquitysoftware/views/gui/__init__.py
ubiquitysoftware/views/gui/main_view.py
ubiquitysoftware/views/gui/menu_bar.py
ubiquitysoftware/views/gui/dialogs/__init__.py
ubiquitysoftware/views/gui/dialogs/about.py
ubiquitysoftware/views/gui/dialogs/base.py
ubiquitysoftware/views/gui/dialogs/choice.py
ubiquitysoftware/views/gui/dialogs/confirm.py
ubiquitysoftware/views/gui/dialogs/create_directory.py
ubiquitysoftware/views/gui/dialogs/form.py
ubiquitysoftware/views/gui/dialogs/open.py
ubiquitysoftware/views/gui/dialogs/preference.py
ubiquitysoftware/views/gui/themes/__init__.py
ubiquitysoftware/views/gui/themes/base.py
ubiquitysoftware/views/gui/themes/sun_valley_dark.py
ubiquitysoftware/views/gui/themes/sun_valley_light.py
ubiquitysoftware/views/gui/themes/sv_ttk/LICENSE
ubiquitysoftware/views/gui/themes/sv_ttk/__init__.py
ubiquitysoftware/views/gui/themes/sv_ttk/sun-valley.tcl
ubiquitysoftware/views/gui/themes/sv_ttk/theme/dark.tcl
ubiquitysoftware/views/gui/themes/sv_ttk/theme/light.tcl
ubiquitysoftware/views/gui/themes/sv_ttk/theme/dark/arrow-down.png
ubiquitysoftware/views/gui/themes/sv_ttk/theme/dark/arrow-right.png
ubiquity_student-1.2.7.dist-info/METADATA
ubiquity_student-1.2.7.dist-info/WHEEL
ubiquity_student-1.2.7.dist-info/entry_points.txt
ubiquity_student-1.2.7.dist-info/top_level.txt
ubiquity_student-1.2.7.dist-info/RECORD
