Metadata-Version: 2.1
Name: ubiquity-student
Version: 1.2.7
Summary: Ubiquity permet le suivi de TP de développement informatique
Home-page: https://gitlab.insa-rouen.fr/cip/ubiquity
License: UNKNOWN
Download-URL: https://gitlab.insa-rouen.fr/cip/ubiquity/-/tags
Project-URL: Documentation, https://gitlab.insa-rouen.fr/cip/ubiquity/-/wikis/home
Project-URL: Bug Tracker, https://gitlab.insa-rouen.fr/cip/ubiquity/-/issues
Platform: UNKNOWN
Classifier: Topic :: Education
Classifier: Development Status :: 3 - Alpha
Classifier: License :: OSI Approved :: GNU General Public License v3 (GPLv3)
Classifier: Intended Audience :: Education
Classifier: Programming Language :: Python :: 3
Classifier: Programming Language :: Python :: 3.7
Classifier: Programming Language :: Python :: 3.8
Classifier: Programming Language :: Python :: 3.9
Classifier: Programming Language :: Python :: 3.10
Classifier: Programming Language :: Python :: 3.11
Classifier: Programming Language :: Python :: 3.12
Classifier: Programming Language :: Python :: 3.13
Classifier: Natural Language :: French
Requires-Python: >=3.7
Requires-Dist: requests
